Workbook

Sheet prices
A1: Date | B1: Russell 3000 | C1: MSCI Developed Ex-US | D1: MSCI Emerging Market | E1: Bloomberg Aggregate Bond | F1: T bill
A2: 42521 | B2: 6180.07 | C2: 4775.97 | D2: 349.56 | E2: 1991.9 | F2: 192.4
A3: 42551 | B3: 6192.78 | C3: 4615.65 | D3: 363.53 | E3: 2027.69 | F3: 192.45
A4: 42580 | B4: 6438.55 | C4: 4849.57 | D4: 381.82 | E4: 2040.51 | F4: 192.49
A5: 42613 | B5: 6454.97 | C5: 4853.02 | D5: 391.31 | E5: 2038.18 | F5: 192.54
A6: 42643 | B6: 6465.12 | C6: 4912.63 | D6: 396.35 | E6: 2036.98 | F6: 192.6
A7: 42674 | B7: 6325.24 | C7: 4812.15 | D7: 397.29 | E7: 2021.4 | F7: 192.64
A8: 42704 | B8: 6608.31 | C8: 4716.31 | D8: 379 | E8: 1973.59 | F8: 192.67
A9: 42734 | B9: 6737.26 | C9: 4877.58 | D9: 379.84 | E9: 1976.37 | F9: 192.73
A10: 42766 | B10: 6864.07 | C10: 5019.07 | D10: 400.63 | E10: 1980.25 | F10: 192.81
A11: 42794 | B11: 7119.35 | C11: 5090.84 | D11: 412.89 | E11: 1993.56 | F11: 192.89
A12: 42825 | B12: 7124.2 | C12: 5230.98 | D12: 423.31 | E12: 1992.51 | F12: 192.93
A13: 42853 | B13: 7199.71 | C13: 5364.08 | D13: 432.58 | E13: 2007.89 | F13: 193.05
... A122: 46171 | B122: 25261.66 | C122: 11598.58 | D122: 962.86 | E122: 2357.7 | F122: 242.04

Sheet asset_info
A1: Asset | B1: Asset Class | C1: Region | D1: Subgroup
A2: =IF(LEN(INDEX(prices!$1:$1,ROW())&"")=0,"",INDEX(prices!$1:$1,ROW())) | B2: Equity | C2: Domestic | D2: US Equity
A3: =IF(LEN(INDEX(prices!$1:$1,ROW())&"")=0,"",INDEX(prices!$1:$1,ROW())) | B3: Equity | C3: Foreign | D3: Developed
A4: =IF(LEN(INDEX(prices!$1:$1,ROW())&"")=0,"",INDEX(prices!$1:$1,ROW())) | B4: Equity | C4: Foreign | D4: Emerging
A5: =IF(LEN(INDEX(prices!$1:$1,ROW())&"")=0,"",INDEX(prices!$1:$1,ROW())) | B5: Fixed Income | C5: Domestic | D5: Bond
A6: =IF(LEN(INDEX(prices!$1:$1,ROW())&"")=0,"",INDEX(prices!$1:$1,ROW())) | B6: Cash | C6: Domestic | D6: Cash
A7: =IF(LEN(INDEX(prices!$1:$1,ROW())&"")=0,"",INDEX(prices!$1:$1,ROW()))
A8: =IF(LEN(INDEX(prices!$1:$1,ROW())&"")=0,"",INDEX(prices!$1:$1,ROW()))
A9: =IF(LEN(INDEX(prices!$1:$1,ROW())&"")=0,"",INDEX(prices!$1:$1,ROW()))
A10: =IF(LEN(INDEX(prices!$1:$1,ROW())&"")=0,"",INDEX(prices!$1:$1,ROW()))
A11: =IF(LEN(INDEX(prices!$1:$1,ROW())&"")=0,"",INDEX(prices!$1:$1,ROW()))
A12: =IF(LEN(INDEX(prices!$1:$1,ROW())&"")=0,"",INDEX(prices!$1:$1,ROW()))
A13: =IF(LEN(INDEX(prices!$1:$1,ROW())&"")=0,"",INDEX(prices!$1:$1,ROW()))
A14: =IF(LEN(INDEX(prices!$1:$1,ROW())&"")=0,"",INDEX(prices!$1:$1,ROW()))
A15: =IF(LEN(INDEX(prices!$1:$1,ROW())&"")=0,"",INDEX(prices!$1:$1,ROW()))
A16: =IF(LEN(INDEX(prices!$1:$1,ROW())&"")=0,"",INDEX(prices!$1:$1,ROW()))
A17: =IF(LEN(INDEX(prices!$1:$1,ROW())&"")=0,"",INDEX(prices!$1:$1,ROW()))
A18: =IF(LEN(INDEX(prices!$1:$1,ROW())&"")=0,"",INDEX(prices!$1:$1,ROW()))
... A200: =IF(LEN(INDEX(prices!$1:$1,ROW())&"")=0,"",INDEX(prices!$1:$1,ROW()))

Sheet expected_returns
A1: Asset | B1: Expected Annual Return
A2: =IF(LEN(INDEX(prices!$1:$1,ROW())&"")=0,"",INDEX(prices!$1:$1,ROW())) | B2: 0.0897
A3: =IF(LEN(INDEX(prices!$1:$1,ROW())&"")=0,"",INDEX(prices!$1:$1,ROW())) | B3: 0.0779
A4: =IF(LEN(INDEX(prices!$1:$1,ROW())&"")=0,"",INDEX(prices!$1:$1,ROW())) | B4: 0.0795
A5: =IF(LEN(INDEX(prices!$1:$1,ROW())&"")=0,"",INDEX(prices!$1:$1,ROW())) | B5: 0.047
A6: =IF(LEN(INDEX(prices!$1:$1,ROW())&"")=0,"",INDEX(prices!$1:$1,ROW())) | B6: 0.0369
A7: =IF(LEN(INDEX(prices!$1:$1,ROW())&"")=0,"",INDEX(prices!$1:$1,ROW()))
A8: =IF(LEN(INDEX(prices!$1:$1,ROW())&"")=0,"",INDEX(prices!$1:$1,ROW()))
A9: =IF(LEN(INDEX(prices!$1:$1,ROW())&"")=0,"",INDEX(prices!$1:$1,ROW()))
A10: =IF(LEN(INDEX(prices!$1:$1,ROW())&"")=0,"",INDEX(prices!$1:$1,ROW()))
A11: =IF(LEN(INDEX(prices!$1:$1,ROW())&"")=0,"",INDEX(prices!$1:$1,ROW()))
A12: =IF(LEN(INDEX(prices!$1:$1,ROW())&"")=0,"",INDEX(prices!$1:$1,ROW()))
A13: =IF(LEN(INDEX(prices!$1:$1,ROW())&"")=0,"",INDEX(prices!$1:$1,ROW()))
A14: =IF(LEN(INDEX(prices!$1:$1,ROW())&"")=0,"",INDEX(prices!$1:$1,ROW()))
A15: =IF(LEN(INDEX(prices!$1:$1,ROW())&"")=0,"",INDEX(prices!$1:$1,ROW()))
A16: =IF(LEN(INDEX(prices!$1:$1,ROW())&"")=0,"",INDEX(prices!$1:$1,ROW()))
A17: =IF(LEN(INDEX(prices!$1:$1,ROW())&"")=0,"",INDEX(prices!$1:$1,ROW()))
A18: =IF(LEN(INDEX(prices!$1:$1,ROW())&"")=0,"",INDEX(prices!$1:$1,ROW()))
... A200: =IF(LEN(INDEX(prices!$1:$1,ROW())&"")=0,"",INDEX(prices!$1:$1,ROW()))

Sheet README
A1: Portfolio Optimizer Excel Template
A2: prices | B2: Paste Date plus price/index levels. The first row after Date contains asset names.
A3: asset_info | B3: Asset names in column A auto-populate from the prices sheet. Fill Asset Class, Region, and Subgroup manually.
A4: expected_returns | B4: Asset names in column A auto-populate from the prices sheet. Fill Expected Annual Return only if using manual expected returns.
A5: optional expected_returns | B5: If this sheet is missing, blank, or mismatched, the app automatically uses historical returns.
A6: classification_guide | B6: Use this sheet to choose consistent labels for Asset Class, Region, and Subgroup.
A7: important | B7: After changing price headers, review asset_info classifications. Excel can fill asset names, but it cannot classify assets automatically.
A8: asset names | B8: Do not manually edit asset_info column A unless formulas do not work. Names must match prices exactly.
A9: expected return format | B9: Enter 8.97% as an Excel percentage or as 0.0897, not 8.97.
A10: minimum required sheets | B10: prices and asset_info. expected_returns is optional.
A11: save before upload | B11: Save the workbook after editing so Excel stores the updated formula results.

Sheet classification_guide
A1: Field | B1: Purpose in the App | C1: Recommended Values | D1: How to Fill It | E1: Example Assets
A2: Asset Class | B2: Defines broad asset bucket for major group constraints. | C2: Equity; Fixed Income; Cash; Alternative; Commodity; Real Estate; Currency; Other | D2: Use Equity for stock/equity indexes or ETFs. Use Fixed Income for bonds. Use Cash for T-bills or money market assets. Use Other only if no standard bucket fits. | E2: Russell 3000 = Equity; Bloomberg Aggregate Bond = Fixed Income; T bill = Cash
A3: Region | B3: Defines geographic exposure. Used for the Foreign Equity constraint. | C3: Domestic; Foreign; Global; US; Developed Ex-US; Emerging Market; International; Other | D3: Use Domestic for the investor's home market. Use Foreign for non-domestic equity when you want it counted in the foreign-equity constraint. Use Global if the asset spans domestic and foreign markets. | E3: Russell 3000 = Domestic; MSCI Developed Ex-US = Foreign; MSCI Emerging Market = Foreign
A4: Subgroup | B4: Defines more specific buckets for optional subgroup constraints. | C4: US Equity; Developed; Emerging; Bond; Government Bond; Corporate Bond; High Yield; Cash; REIT; Commodity; Gold; Sector; Other | D4: Use Developed for developed-market foreign equity. Use Emerging for emerging-market equity. Use Bond for broad aggregate bonds. Use Sector for sector ETFs. Use Other for custom assets. | E4: MSCI Developed Ex-US = Developed; MSCI Emerging Market = Emerging; T bill = Cash
A5: Built-in constraint labels | B5: Shows which exact labels currently drive the built-in constraints. | C5: Asset Class = Equity / Fixed Income / Cash; Region = Foreign; Subgroup = Developed / Emerging | D5: Use these exact labels when you want those built-in constraints to work. Other labels can still be used, but they will not trigger those constraints. | E5: Foreign Equity Max = Asset Class Equity and Region Foreign
A6: Future datasets | B6: Shows the minimum work needed when changing the asset universe. | C6: 1. Paste new prices; 2. Fill asset_info; 3. Update expected_returns if using manual assumptions. | D6: Asset names must match exactly across prices, asset_info, and expected_returns. | E6: If prices column says VTI, asset_info Asset must also say VTI
A7: Auto-populated asset names | B7: Asset names in asset_info and expected_returns are formula-linked to prices row 1. | C7: Formula pattern: =IFERROR(INDEX(prices!$1:$1,ROW()),"") | D7: Change asset headers in prices, then review classifications and expected returns. | E7: If formulas do not calculate, open and save in Excel or paste names as values.
A8: Template workflow | B8: 1. Replace prices data; 2. Save workbook; 3. Fill classifications; 4. Optional expected returns; 5. Upload to app. | C8: Asset Class, Region, and Subgroup still require judgment. | D8: Do not leave classifications blank for active assets. | E8: Expected returns are optional.
